khmerspell/__init__.py
khmerspell/khnormal.py
khmerspell-0.1.1.dist-info/LICENSE
khmerspell-0.1.1.dist-info/METADATA
khmerspell-0.1.1.dist-info/WHEEL
khmerspell-0.1.1.dist-info/top_level.txt
khmerspell-0.1.1.dist-info/RECORD
