Metadata-Version: 2.2
Name: khmerspell
Version: 0.1.1
Summary: Khmer Spelling or Unicode Character Reordering based on the [khmer character specification](https://github.com/sillsdev/khmer-character-specification/blob/master/specification.md).
Home-page: https://github.com/maohieng/khmerspell
Author: Hieng MAO
Author-email: maohieng@gmail.com
License: Apache License 2.0
Classifier: Programming Language :: Python :: 3
Classifier: Operating System :: OS Independent
Classifier: Intended Audience :: Developers
Classifier: Natural Language :: English
Requires-Python: >=3.5
License-File: LICENSE
Dynamic: author
Dynamic: author-email
Dynamic: classifier
Dynamic: description
Dynamic: description-content-type
Dynamic: home-page
Dynamic: license
Dynamic: requires-python
Dynamic: summary
